coqui_stt_model_manager/__init__.py
coqui_stt_model_manager/__main__.py
coqui_stt_model_manager/modelmanager.py
coqui_stt_model_manager/server.py
coqui_stt_model_manager/static/bootstrap-icons.css
coqui_stt_model_manager/static/bootstrap.min.css
coqui_stt_model_manager/static/coqui-STT-logo-green.png
coqui_stt_model_manager/static/downsampling_worker.js
coqui_stt_model_manager/static/style.css
coqui_stt_model_manager/static/build/precache-manifest.00e00f8764d1676cb57dc6b85137087d.js
coqui_stt_model_manager/static/build/service-worker.js
coqui_stt_model_manager/static/build/static/css/bundle.min.css
coqui_stt_model_manager/static/build/static/js/bundle.min.js
coqui_stt_model_manager/static/build/static/js/bundle.min.js.LICENSE.txt
coqui_stt_model_manager/static/build/static/js/bundle.min.js.map
coqui_stt_model_manager/static/fonts/bootstrap-icons.woff
coqui_stt_model_manager/static/fonts/bootstrap-icons.woff2
coqui_stt_model_manager/templates/base.html
coqui_stt_model_manager/templates/index.html
coqui_stt_model_manager/templates/transcribe.html
coqui_stt_model_manager-0.0.21.dist-info/LICENSE
coqui_stt_model_manager-0.0.21.dist-info/METADATA
coqui_stt_model_manager-0.0.21.dist-info/WHEEL
coqui_stt_model_manager-0.0.21.dist-info/entry_points.txt
coqui_stt_model_manager-0.0.21.dist-info/top_level.txt
coqui_stt_model_manager-0.0.21.dist-info/RECORD
